README.md
setup.py
pySMP/__init__.py
pySMP/model.py
pySMP.egg-info/PKG-INFO
pySMP.egg-info/SOURCES.txt
pySMP.egg-info/dependency_links.txt
pySMP.egg-info/top_level.txt
pySMP/lib/libsmpDyn.dylib
pySMP/lib/libsmpDyn.so
pySMP/lib/smpDyn.dll