Metadata-Version: 1.1
Name: pySMP
Version: 0.1.2
Summary: KTAB
Home-page: https://github.com/kapsarc/pySMP
Author: King Abdullah Petroleum Studies and Research Center
Author-email: ktab@kapsarc.org
License: UNKNOWN
Platform: UNKNOWN
Classifier: Programming Language :: Python :: 3
Classifier: License :: OSI Approved :: MIT License
Classifier: Operating System :: OS Independent
